{
    "back_pack": {
        "precision": 1.0,
        "recall": 1.0,
        "f1-score": 1.0,
        "support": 8
    },
    "bike": {
        "precision": 1.0,
        "recall": 1.0,
        "f1-score": 1.0,
        "support": 6
    },
    "bike_helmet": {
        "precision": 1.0,
        "recall": 1.0,
        "f1-score": 1.0,
        "support": 8
    },
    "bookcase": {
        "precision": 1.0,
        "recall": 1.0,
        "f1-score": 1.0,
        "support": 5
    },
    "bottle": {
        "precision": 1.0,
        "recall": 1.0,
        "f1-score": 1.0,
        "support": 3
    },
    "calculator": {
        "precision": 1.0,
        "recall": 1.0,
        "f1-score": 1.0,
        "support": 4
    },
    "desk_chair": {
        "precision": 1.0,
        "recall": 1.0,
        "f1-score": 1.0,
        "support": 5
    },
    "desk_lamp": {
        "precision": 1.0,
        "recall": 1.0,
        "f1-score": 1.0,
        "support": 4
    },
    "desktop_computer": {
        "precision": 1.0,
        "recall": 1.0,
        "f1-score": 1.0,
        "support": 4
    },
    "file_cabinet": {
        "precision": 1.0,
        "recall": 1.0,
        "f1-score": 1.0,
        "support": 3
    },
    "headphones": {
        "precision": 0.75,
        "recall": 1.0,
        "f1-score": 0.8571428571428571,
        "support": 3
    },
    "keyboard": {
        "precision": 1.0,
        "recall": 1.0,
        "f1-score": 1.0,
        "support": 2
    },
    "laptop_computer": {
        "precision": 1.0,
        "recall": 0.75,
        "f1-score": 0.8571428571428571,
        "support": 4
    },
    "letter_tray": {
        "precision": 1.0,
        "recall": 1.0,
        "f1-score": 1.0,
        "support": 3
    },
    "mobile_phone": {
        "precision": 1.0,
        "recall": 1.0,
        "f1-score": 1.0,
        "support": 4
    },
    "monitor": {
        "precision": 1.0,
        "recall": 1.0,
        "f1-score": 1.0,
        "support": 8
    },
    "mouse": {
        "precision": 1.0,
        "recall": 1.0,
        "f1-score": 1.0,
        "support": 2
    },
    "mug": {
        "precision": 1.0,
        "recall": 1.0,
        "f1-score": 1.0,
        "support": 2
    },
    "paper_notebook": {
        "precision": 0.75,
        "recall": 1.0,
        "f1-score": 0.8571428571428571,
        "support": 3
    },
    "pen": {
        "precision": 1.0,
        "recall": 1.0,
        "f1-score": 1.0,
        "support": 5
    },
    "phone": {
        "precision": 1.0,
        "recall": 1.0,
        "f1-score": 1.0,
        "support": 7
    },
    "printer": {
        "precision": 1.0,
        "recall": 1.0,
        "f1-score": 1.0,
        "support": 2
    },
    "projector": {
        "precision": 1.0,
        "recall": 1.0,
        "f1-score": 1.0,
        "support": 6
    },
    "punchers": {
        "precision": 1.0,
        "recall": 1.0,
        "f1-score": 1.0,
        "support": 6
    },
    "ring_binder": {
        "precision": 1.0,
        "recall": 1.0,
        "f1-score": 1.0,
        "support": 6
    },
    "ruler": {
        "precision": 1.0,
        "recall": 1.0,
        "f1-score": 1.0,
        "support": 2
    },
    "scissors": {
        "precision": 1.0,
        "recall": 1.0,
        "f1-score": 1.0,
        "support": 3
    },
    "speaker": {
        "precision": 1.0,
        "recall": 0.9166666666666666,
        "f1-score": 0.9565217391304348,
        "support": 12
    },
    "stapler": {
        "precision": 1.0,
        "recall": 1.0,
        "f1-score": 1.0,
        "support": 8
    },
    "tape_dispenser": {
        "precision": 1.0,
        "recall": 1.0,
        "f1-score": 1.0,
        "support": 7
    },
    "trash_can": {
        "precision": 1.0,
        "recall": 1.0,
        "f1-score": 1.0,
        "support": 4
    },
    "accuracy": 0.9865771812080537,
    "macro avg": {
        "precision": 0.9838709677419355,
        "recall": 0.989247311827957,
        "f1-score": 0.9847725906631938,
        "support": 149
    },
    "weighted avg": {
        "precision": 0.9899328859060402,
        "recall": 0.9865771812080537,
        "f1-score": 0.9869106673892202,
        "support": 149
    }
}