{
    "back_pack": {
        "precision": 0.8275862068965517,
        "recall": 1.0,
        "f1-score": 0.9056603773584906,
        "support": 24
    },
    "bike": {
        "precision": 1.0,
        "recall": 1.0,
        "f1-score": 1.0,
        "support": 16
    },
    "bike_helmet": {
        "precision": 1.0,
        "recall": 0.8695652173913043,
        "f1-score": 0.9302325581395349,
        "support": 23
    },
    "bookcase": {
        "precision": 0.35,
        "recall": 1.0,
        "f1-score": 0.5185185185185185,
        "support": 7
    },
    "bottle": {
        "precision": 0.8461538461538461,
        "recall": 1.0,
        "f1-score": 0.9166666666666666,
        "support": 11
    },
    "calculator": {
        "precision": 0.8518518518518519,
        "recall": 0.8846153846153846,
        "f1-score": 0.8679245283018868,
        "support": 26
    },
    "desk_chair": {
        "precision": 0.9459459459459459,
        "recall": 1.0,
        "f1-score": 0.9722222222222222,
        "support": 35
    },
    "desk_lamp": {
        "precision": 0.75,
        "recall": 0.46153846153846156,
        "f1-score": 0.5714285714285714,
        "support": 13
    },
    "desktop_computer": {
        "precision": 0.6153846153846154,
        "recall": 0.5,
        "f1-score": 0.5517241379310345,
        "support": 16
    },
    "file_cabinet": {
        "precision": 0.8333333333333334,
        "recall": 0.7142857142857143,
        "f1-score": 0.7692307692307692,
        "support": 14
    },
    "headphones": {
        "precision": 0.9523809523809523,
        "recall": 0.9090909090909091,
        "f1-score": 0.9302325581395349,
        "support": 22
    },
    "keyboard": {
        "precision": 0.9473684210526315,
        "recall": 0.8181818181818182,
        "f1-score": 0.8780487804878049,
        "support": 22
    },
    "laptop_computer": {
        "precision": 0.9473684210526315,
        "recall": 0.72,
        "f1-score": 0.8181818181818181,
        "support": 25
    },
    "letter_tray": {
        "precision": 0.8,
        "recall": 0.2857142857142857,
        "f1-score": 0.4210526315789473,
        "support": 14
    },
    "mobile_phone": {
        "precision": 0.6818181818181818,
        "recall": 0.6,
        "f1-score": 0.6382978723404256,
        "support": 25
    },
    "monitor": {
        "precision": 0.9666666666666667,
        "recall": 0.7631578947368421,
        "f1-score": 0.8529411764705883,
        "support": 38
    },
    "mouse": {
        "precision": 0.7407407407407407,
        "recall": 0.8,
        "f1-score": 0.7692307692307692,
        "support": 25
    },
    "mug": {
        "precision": 1.0,
        "recall": 1.0,
        "f1-score": 1.0,
        "support": 22
    },
    "paper_notebook": {
        "precision": 0.65625,
        "recall": 0.9130434782608695,
        "f1-score": 0.7636363636363634,
        "support": 23
    },
    "pen": {
        "precision": 0.6,
        "recall": 0.8888888888888888,
        "f1-score": 0.7164179104477612,
        "support": 27
    },
    "phone": {
        "precision": 1.0,
        "recall": 0.9090909090909091,
        "f1-score": 0.9523809523809523,
        "support": 11
    },
    "printer": {
        "precision": 0.8461538461538461,
        "recall": 0.7333333333333333,
        "f1-score": 0.7857142857142856,
        "support": 15
    },
    "projector": {
        "precision": 0.7727272727272727,
        "recall": 0.68,
        "f1-score": 0.7234042553191491,
        "support": 25
    },
    "punchers": {
        "precision": 0.8181818181818182,
        "recall": 0.4090909090909091,
        "f1-score": 0.5454545454545455,
        "support": 22
    },
    "ring_binder": {
        "precision": 0.8157894736842105,
        "recall": 0.8857142857142857,
        "f1-score": 0.8493150684931505,
        "support": 35
    },
    "ruler": {
        "precision": 0.18181818181818182,
        "recall": 0.3333333333333333,
        "f1-score": 0.23529411764705885,
        "support": 6
    },
    "scissors": {
        "precision": 0.9,
        "recall": 0.45,
        "f1-score": 0.6,
        "support": 20
    },
    "speaker": {
        "precision": 0.6774193548387096,
        "recall": 0.84,
        "f1-score": 0.75,
        "support": 25
    },
    "stapler": {
        "precision": 0.35,
        "recall": 0.3684210526315789,
        "f1-score": 0.358974358974359,
        "support": 19
    },
    "tape_dispenser": {
        "precision": 0.38235294117647056,
        "recall": 0.7222222222222222,
        "f1-score": 0.4999999999999999,
        "support": 18
    },
    "trash_can": {
        "precision": 1.0,
        "recall": 0.5,
        "f1-score": 0.6666666666666666,
        "support": 16
    },
    "accuracy": 0.7640625,
    "macro avg": {
        "precision": 0.7760416797373696,
        "recall": 0.7406221967135822,
        "f1-score": 0.7341565316439316,
        "support": 640
    },
    "weighted avg": {
        "precision": 0.8039538408967772,
        "recall": 0.7640625,
        "f1-score": 0.7653495624181994,
        "support": 640
    }
}