{
    "back_pack": {
        "precision": 0.8888888888888888,
        "recall": 1.0,
        "f1-score": 0.9411764705882353,
        "support": 24
    },
    "bike": {
        "precision": 1.0,
        "recall": 1.0,
        "f1-score": 1.0,
        "support": 16
    },
    "bike_helmet": {
        "precision": 0.9090909090909091,
        "recall": 0.8695652173913043,
        "f1-score": 0.888888888888889,
        "support": 23
    },
    "bookcase": {
        "precision": 0.75,
        "recall": 0.8571428571428571,
        "f1-score": 0.7999999999999999,
        "support": 7
    },
    "bottle": {
        "precision": 0.9166666666666666,
        "recall": 1.0,
        "f1-score": 0.9565217391304348,
        "support": 11
    },
    "calculator": {
        "precision": 0.8148148148148148,
        "recall": 0.8461538461538461,
        "f1-score": 0.830188679245283,
        "support": 26
    },
    "desk_chair": {
        "precision": 1.0,
        "recall": 0.9714285714285714,
        "f1-score": 0.9855072463768115,
        "support": 35
    },
    "desk_lamp": {
        "precision": 0.9285714285714286,
        "recall": 1.0,
        "f1-score": 0.962962962962963,
        "support": 13
    },
    "desktop_computer": {
        "precision": 0.4,
        "recall": 0.25,
        "f1-score": 0.3076923076923077,
        "support": 16
    },
    "file_cabinet": {
        "precision": 0.8235294117647058,
        "recall": 1.0,
        "f1-score": 0.9032258064516129,
        "support": 14
    },
    "headphones": {
        "precision": 0.9523809523809523,
        "recall": 0.9090909090909091,
        "f1-score": 0.9302325581395349,
        "support": 22
    },
    "keyboard": {
        "precision": 0.85,
        "recall": 0.7727272727272727,
        "f1-score": 0.8095238095238095,
        "support": 22
    },
    "laptop_computer": {
        "precision": 0.9473684210526315,
        "recall": 0.72,
        "f1-score": 0.8181818181818181,
        "support": 25
    },
    "letter_tray": {
        "precision": 0.7142857142857143,
        "recall": 0.35714285714285715,
        "f1-score": 0.4761904761904762,
        "support": 14
    },
    "mobile_phone": {
        "precision": 0.6111111111111112,
        "recall": 0.44,
        "f1-score": 0.5116279069767442,
        "support": 25
    },
    "monitor": {
        "precision": 0.8648648648648649,
        "recall": 0.8421052631578947,
        "f1-score": 0.8533333333333334,
        "support": 38
    },
    "mouse": {
        "precision": 0.8571428571428571,
        "recall": 0.72,
        "f1-score": 0.782608695652174,
        "support": 25
    },
    "mug": {
        "precision": 0.9166666666666666,
        "recall": 1.0,
        "f1-score": 0.9565217391304348,
        "support": 22
    },
    "paper_notebook": {
        "precision": 0.7407407407407407,
        "recall": 0.8695652173913043,
        "f1-score": 0.7999999999999999,
        "support": 23
    },
    "pen": {
        "precision": 0.7222222222222222,
        "recall": 0.9629629629629629,
        "f1-score": 0.8253968253968254,
        "support": 27
    },
    "phone": {
        "precision": 0.8333333333333334,
        "recall": 0.9090909090909091,
        "f1-score": 0.8695652173913043,
        "support": 11
    },
    "printer": {
        "precision": 0.46153846153846156,
        "recall": 0.8,
        "f1-score": 0.5853658536585367,
        "support": 15
    },
    "projector": {
        "precision": 0.5,
        "recall": 0.48,
        "f1-score": 0.4897959183673469,
        "support": 25
    },
    "punchers": {
        "precision": 0.8571428571428571,
        "recall": 0.5454545454545454,
        "f1-score": 0.6666666666666665,
        "support": 22
    },
    "ring_binder": {
        "precision": 0.7837837837837838,
        "recall": 0.8285714285714286,
        "f1-score": 0.8055555555555555,
        "support": 35
    },
    "ruler": {
        "precision": 0.3333333333333333,
        "recall": 0.6666666666666666,
        "f1-score": 0.4444444444444444,
        "support": 6
    },
    "scissors": {
        "precision": 1.0,
        "recall": 0.65,
        "f1-score": 0.787878787878788,
        "support": 20
    },
    "speaker": {
        "precision": 1.0,
        "recall": 0.6,
        "f1-score": 0.7499999999999999,
        "support": 25
    },
    "stapler": {
        "precision": 0.9,
        "recall": 0.47368421052631576,
        "f1-score": 0.6206896551724138,
        "support": 19
    },
    "tape_dispenser": {
        "precision": 0.4444444444444444,
        "recall": 0.8888888888888888,
        "f1-score": 0.5925925925925926,
        "support": 18
    },
    "trash_can": {
        "precision": 0.5,
        "recall": 0.75,
        "f1-score": 0.6,
        "support": 16
    },
    "accuracy": 0.7765625,
    "macro avg": {
        "precision": 0.781352318833593,
        "recall": 0.7735561814125335,
        "f1-score": 0.7597527727609464,
        "support": 640
    },
    "weighted avg": {
        "precision": 0.8036759550468917,
        "recall": 0.7765625,
        "f1-score": 0.7748627940295656,
        "support": 640
    }
}