{
    "back_pack": {
        "precision": 0.96,
        "recall": 1.0,
        "f1-score": 0.9795918367346939,
        "support": 24
    },
    "bike": {
        "precision": 1.0,
        "recall": 1.0,
        "f1-score": 1.0,
        "support": 16
    },
    "bike_helmet": {
        "precision": 1.0,
        "recall": 0.9130434782608695,
        "f1-score": 0.9545454545454545,
        "support": 23
    },
    "bookcase": {
        "precision": 1.0,
        "recall": 1.0,
        "f1-score": 1.0,
        "support": 7
    },
    "bottle": {
        "precision": 0.9166666666666666,
        "recall": 1.0,
        "f1-score": 0.9565217391304348,
        "support": 11
    },
    "calculator": {
        "precision": 0.8,
        "recall": 0.9230769230769231,
        "f1-score": 0.8571428571428571,
        "support": 26
    },
    "desk_chair": {
        "precision": 1.0,
        "recall": 0.9714285714285714,
        "f1-score": 0.9855072463768115,
        "support": 35
    },
    "desk_lamp": {
        "precision": 0.8,
        "recall": 0.9230769230769231,
        "f1-score": 0.8571428571428571,
        "support": 13
    },
    "desktop_computer": {
        "precision": 0.5789473684210527,
        "recall": 0.6875,
        "f1-score": 0.6285714285714286,
        "support": 16
    },
    "file_cabinet": {
        "precision": 0.8235294117647058,
        "recall": 1.0,
        "f1-score": 0.9032258064516129,
        "support": 14
    },
    "headphones": {
        "precision": 0.9565217391304348,
        "recall": 1.0,
        "f1-score": 0.9777777777777777,
        "support": 22
    },
    "keyboard": {
        "precision": 0.8823529411764706,
        "recall": 0.6818181818181818,
        "f1-score": 0.7692307692307693,
        "support": 22
    },
    "laptop_computer": {
        "precision": 0.9565217391304348,
        "recall": 0.88,
        "f1-score": 0.9166666666666666,
        "support": 25
    },
    "letter_tray": {
        "precision": 0.5238095238095238,
        "recall": 0.7857142857142857,
        "f1-score": 0.6285714285714286,
        "support": 14
    },
    "mobile_phone": {
        "precision": 0.95,
        "recall": 0.76,
        "f1-score": 0.8444444444444444,
        "support": 25
    },
    "monitor": {
        "precision": 1.0,
        "recall": 0.6578947368421053,
        "f1-score": 0.7936507936507937,
        "support": 38
    },
    "mouse": {
        "precision": 0.8846153846153846,
        "recall": 0.92,
        "f1-score": 0.9019607843137256,
        "support": 25
    },
    "mug": {
        "precision": 0.9166666666666666,
        "recall": 1.0,
        "f1-score": 0.9565217391304348,
        "support": 22
    },
    "paper_notebook": {
        "precision": 0.7419354838709677,
        "recall": 1.0,
        "f1-score": 0.8518518518518519,
        "support": 23
    },
    "pen": {
        "precision": 0.9130434782608695,
        "recall": 0.7777777777777778,
        "f1-score": 0.84,
        "support": 27
    },
    "phone": {
        "precision": 1.0,
        "recall": 1.0,
        "f1-score": 1.0,
        "support": 11
    },
    "printer": {
        "precision": 0.5555555555555556,
        "recall": 0.6666666666666666,
        "f1-score": 0.606060606060606,
        "support": 15
    },
    "projector": {
        "precision": 0.9333333333333333,
        "recall": 0.56,
        "f1-score": 0.7000000000000001,
        "support": 25
    },
    "punchers": {
        "precision": 0.7333333333333333,
        "recall": 0.5,
        "f1-score": 0.5945945945945945,
        "support": 22
    },
    "ring_binder": {
        "precision": 0.8333333333333334,
        "recall": 0.7142857142857143,
        "f1-score": 0.7692307692307692,
        "support": 35
    },
    "ruler": {
        "precision": 0.2222222222222222,
        "recall": 0.6666666666666666,
        "f1-score": 0.3333333333333333,
        "support": 6
    },
    "scissors": {
        "precision": 1.0,
        "recall": 0.85,
        "f1-score": 0.9189189189189189,
        "support": 20
    },
    "speaker": {
        "precision": 0.6176470588235294,
        "recall": 0.84,
        "f1-score": 0.711864406779661,
        "support": 25
    },
    "stapler": {
        "precision": 0.6923076923076923,
        "recall": 0.47368421052631576,
        "f1-score": 0.5625,
        "support": 19
    },
    "tape_dispenser": {
        "precision": 0.5862068965517241,
        "recall": 0.9444444444444444,
        "f1-score": 0.7234042553191489,
        "support": 18
    },
    "trash_can": {
        "precision": 1.0,
        "recall": 0.6875,
        "f1-score": 0.8148148148148148,
        "support": 16
    },
    "accuracy": 0.8234375,
    "macro avg": {
        "precision": 0.831566123515287,
        "recall": 0.831760599373724,
        "f1-score": 0.817343457444706,
        "support": 640
    },
    "weighted avg": {
        "precision": 0.8562703294650229,
        "recall": 0.8234375,
        "f1-score": 0.8272058962086847,
        "support": 640
    }
}