{
    "aeroplane": {
        "precision": 0.9442870632672332,
        "recall": 0.9354536950420954,
        "f1-score": 0.9398496240601504,
        "support": 1069
    },
    "bicycle": {
        "precision": 0.8486238532110092,
        "recall": 0.7040913415794482,
        "f1-score": 0.7696307852314093,
        "support": 1051
    },
    "bus": {
        "precision": 0.7150701647345943,
        "recall": 0.824771287825475,
        "f1-score": 0.7660130718954248,
        "support": 1421
    },
    "car": {
        "precision": 0.6913678618857901,
        "recall": 0.8514883873078182,
        "f1-score": 0.7631193198475519,
        "support": 3057
    },
    "horse": {
        "precision": 0.9210716871832005,
        "recall": 0.931185944363104,
        "f1-score": 0.9261012013105206,
        "support": 1366
    },
    "knife": {
        "precision": 0.8016,
        "recall": 0.7477611940298508,
        "f1-score": 0.7737451737451738,
        "support": 670
    },
    "motorcycle": {
        "precision": 0.7926337033299697,
        "recall": 0.8961779806046777,
        "f1-score": 0.841231593038822,
        "support": 1753
    },
    "person": {
        "precision": 0.7382875605815832,
        "recall": 0.7522633744855967,
        "f1-score": 0.7452099470036689,
        "support": 1215
    },
    "plant": {
        "precision": 0.875,
        "recall": 0.9264705882352942,
        "f1-score": 0.9,
        "support": 1360
    },
    "skateboard": {
        "precision": 0.7906976744186046,
        "recall": 0.7434402332361516,
        "f1-score": 0.7663410969196093,
        "support": 686
    },
    "train": {
        "precision": 0.7960872836719338,
        "recall": 0.8144726712856043,
        "f1-score": 0.8051750380517503,
        "support": 1299
    },
    "truck": {
        "precision": 0.7238689547581904,
        "recall": 0.2780107849011384,
        "f1-score": 0.4017316017316018,
        "support": 1669
    },
    "accuracy": 0.7862903225806451,
    "macro avg": {
        "precision": 0.8032163172535091,
        "recall": 0.7837989569080213,
        "f1-score": 0.7831790377363069,
        "support": 16616
    },
    "weighted avg": {
        "precision": 0.787638918066857,
        "recall": 0.7862903225806451,
        "f1-score": 0.7742318563521874,
        "support": 16616
    }
}