{
    "back_pack": {
        "precision": 1.0,
        "recall": 0.5977011494252874,
        "f1-score": 0.7482014388489209,
        "support": 87
    },
    "bike": {
        "precision": 0.9871794871794872,
        "recall": 1.0,
        "f1-score": 0.9935483870967742,
        "support": 77
    },
    "bike_helmet": {
        "precision": 1.0,
        "recall": 0.7910447761194029,
        "f1-score": 0.8833333333333333,
        "support": 67
    },
    "bookcase": {
        "precision": 0.6836734693877551,
        "recall": 0.8701298701298701,
        "f1-score": 0.7657142857142857,
        "support": 77
    },
    "bottle": {
        "precision": 0.5925925925925926,
        "recall": 0.5161290322580645,
        "f1-score": 0.5517241379310345,
        "support": 31
    },
    "calculator": {
        "precision": 0.7572815533980582,
        "recall": 0.8764044943820225,
        "f1-score": 0.8125,
        "support": 89
    },
    "desk_chair": {
        "precision": 0.8837209302325582,
        "recall": 0.8837209302325582,
        "f1-score": 0.8837209302325582,
        "support": 86
    },
    "desk_lamp": {
        "precision": 0.875,
        "recall": 0.532608695652174,
        "f1-score": 0.6621621621621623,
        "support": 92
    },
    "desktop_computer": {
        "precision": 0.42718446601941745,
        "recall": 0.4782608695652174,
        "f1-score": 0.4512820512820513,
        "support": 92
    },
    "file_cabinet": {
        "precision": 0.6617647058823529,
        "recall": 0.5921052631578947,
        "f1-score": 0.625,
        "support": 76
    },
    "headphones": {
        "precision": 0.6666666666666666,
        "recall": 0.8936170212765957,
        "f1-score": 0.7636363636363636,
        "support": 94
    },
    "keyboard": {
        "precision": 0.7962962962962963,
        "recall": 0.9052631578947369,
        "f1-score": 0.8472906403940885,
        "support": 95
    },
    "laptop_computer": {
        "precision": 0.7107438016528925,
        "recall": 0.9052631578947369,
        "f1-score": 0.7962962962962963,
        "support": 95
    },
    "letter_tray": {
        "precision": 0.5765765765765766,
        "recall": 0.6881720430107527,
        "f1-score": 0.6274509803921569,
        "support": 93
    },
    "mobile_phone": {
        "precision": 0.5454545454545454,
        "recall": 0.8842105263157894,
        "f1-score": 0.6746987951807227,
        "support": 95
    },
    "monitor": {
        "precision": 0.8837209302325582,
        "recall": 0.8085106382978723,
        "f1-score": 0.8444444444444444,
        "support": 94
    },
    "mouse": {
        "precision": 0.465,
        "recall": 0.9789473684210527,
        "f1-score": 0.6305084745762712,
        "support": 95
    },
    "mug": {
        "precision": 0.9634146341463414,
        "recall": 0.8876404494382022,
        "f1-score": 0.9239766081871345,
        "support": 89
    },
    "paper_notebook": {
        "precision": 0.4868421052631579,
        "recall": 0.4065934065934066,
        "f1-score": 0.4431137724550898,
        "support": 91
    },
    "pen": {
        "precision": 0.8909090909090909,
        "recall": 0.5444444444444444,
        "f1-score": 0.6758620689655171,
        "support": 90
    },
    "phone": {
        "precision": 0.6666666666666666,
        "recall": 0.7954545454545454,
        "f1-score": 0.7253886010362695,
        "support": 88
    },
    "printer": {
        "precision": 0.8058252427184466,
        "recall": 0.8736842105263158,
        "f1-score": 0.8383838383838383,
        "support": 95
    },
    "projector": {
        "precision": 0.7980769230769231,
        "recall": 0.8924731182795699,
        "f1-score": 0.8426395939086294,
        "support": 93
    },
    "punchers": {
        "precision": 0.48484848484848486,
        "recall": 0.17204301075268819,
        "f1-score": 0.25396825396825395,
        "support": 93
    },
    "ring_binder": {
        "precision": 0.31788079470198677,
        "recall": 0.5647058823529412,
        "f1-score": 0.4067796610169491,
        "support": 85
    },
    "ruler": {
        "precision": 0.75,
        "recall": 0.6,
        "f1-score": 0.6666666666666665,
        "support": 70
    },
    "scissors": {
        "precision": 0.9375,
        "recall": 0.3157894736842105,
        "f1-score": 0.4724409448818897,
        "support": 95
    },
    "speaker": {
        "precision": 0.6666666666666666,
        "recall": 0.44680851063829785,
        "f1-score": 0.535031847133758,
        "support": 94
    },
    "stapler": {
        "precision": 0.391304347826087,
        "recall": 0.2872340425531915,
        "f1-score": 0.3312883435582822,
        "support": 94
    },
    "tape_dispenser": {
        "precision": 0.47540983606557374,
        "recall": 0.31868131868131866,
        "f1-score": 0.381578947368421,
        "support": 91
    },
    "trash_can": {
        "precision": 0.6904761904761905,
        "recall": 0.4915254237288136,
        "f1-score": 0.5742574257425742,
        "support": 59
    },
    "accuracy": 0.6739293764087152,
    "macro avg": {
        "precision": 0.7044734517721734,
        "recall": 0.6709408655213539,
        "f1-score": 0.6655770740256367,
        "support": 2662
    },
    "weighted avg": {
        "precision": 0.7024161362684622,
        "recall": 0.6739293764087152,
        "f1-score": 0.6648214627616026,
        "support": 2662
    }
}