{
    "back_pack": {
        "precision": 1.0,
        "recall": 1.0,
        "f1-score": 1.0,
        "support": 7
    },
    "bike": {
        "precision": 1.0,
        "recall": 1.0,
        "f1-score": 1.0,
        "support": 16
    },
    "bike_helmet": {
        "precision": 0.9047619047619048,
        "recall": 1.0,
        "f1-score": 0.9500000000000001,
        "support": 19
    },
    "bookcase": {
        "precision": 0.4,
        "recall": 0.5714285714285714,
        "f1-score": 0.47058823529411764,
        "support": 7
    },
    "bottle": {
        "precision": 1.0,
        "recall": 1.0,
        "f1-score": 1.0,
        "support": 11
    },
    "calculator": {
        "precision": 0.8,
        "recall": 0.5714285714285714,
        "f1-score": 0.6666666666666666,
        "support": 7
    },
    "desk_chair": {
        "precision": 1.0,
        "recall": 0.875,
        "f1-score": 0.9333333333333333,
        "support": 8
    },
    "desk_lamp": {
        "precision": 1.0,
        "recall": 0.7777777777777778,
        "f1-score": 0.8750000000000001,
        "support": 9
    },
    "desktop_computer": {
        "precision": 0.5,
        "recall": 0.6,
        "f1-score": 0.5454545454545454,
        "support": 10
    },
    "file_cabinet": {
        "precision": 0.8333333333333334,
        "recall": 1.0,
        "f1-score": 0.9090909090909091,
        "support": 10
    },
    "headphones": {
        "precision": 1.0,
        "recall": 1.0,
        "f1-score": 1.0,
        "support": 8
    },
    "keyboard": {
        "precision": 0.625,
        "recall": 1.0,
        "f1-score": 0.7692307692307693,
        "support": 5
    },
    "laptop_computer": {
        "precision": 0.9411764705882353,
        "recall": 0.8421052631578947,
        "f1-score": 0.8888888888888888,
        "support": 19
    },
    "letter_tray": {
        "precision": 0.8571428571428571,
        "recall": 0.5454545454545454,
        "f1-score": 0.6666666666666665,
        "support": 11
    },
    "mobile_phone": {
        "precision": 0.9375,
        "recall": 0.5769230769230769,
        "f1-score": 0.7142857142857143,
        "support": 26
    },
    "monitor": {
        "precision": 0.9230769230769231,
        "recall": 0.7058823529411765,
        "f1-score": 0.8000000000000002,
        "support": 17
    },
    "mouse": {
        "precision": 0.875,
        "recall": 1.0,
        "f1-score": 0.9333333333333333,
        "support": 7
    },
    "mug": {
        "precision": 1.0,
        "recall": 1.0,
        "f1-score": 1.0,
        "support": 3
    },
    "paper_notebook": {
        "precision": 0.4444444444444444,
        "recall": 0.8,
        "f1-score": 0.5714285714285714,
        "support": 5
    },
    "pen": {
        "precision": 0.5555555555555556,
        "recall": 1.0,
        "f1-score": 0.7142857142857143,
        "support": 5
    },
    "phone": {
        "precision": 1.0,
        "recall": 0.875,
        "f1-score": 0.9333333333333333,
        "support": 8
    },
    "printer": {
        "precision": 0.4375,
        "recall": 0.7,
        "f1-score": 0.5384615384615384,
        "support": 10
    },
    "projector": {
        "precision": 0.7647058823529411,
        "recall": 0.7222222222222222,
        "f1-score": 0.7428571428571428,
        "support": 18
    },
    "punchers": {
        "precision": 0.6875,
        "recall": 0.8461538461538461,
        "f1-score": 0.7586206896551724,
        "support": 13
    },
    "ring_binder": {
        "precision": 0.3076923076923077,
        "recall": 0.8,
        "f1-score": 0.4444444444444444,
        "support": 5
    },
    "ruler": {
        "precision": 0.0,
        "recall": 0.0,
        "f1-score": 0.0,
        "support": 2
    },
    "scissors": {
        "precision": 1.0,
        "recall": 0.9230769230769231,
        "f1-score": 0.9600000000000001,
        "support": 13
    },
    "speaker": {
        "precision": 0.9473684210526315,
        "recall": 0.8571428571428571,
        "f1-score": 0.9,
        "support": 21
    },
    "stapler": {
        "precision": 0.75,
        "recall": 0.75,
        "f1-score": 0.75,
        "support": 16
    },
    "tape_dispenser": {
        "precision": 1.0,
        "recall": 0.7647058823529411,
        "f1-score": 0.8666666666666666,
        "support": 17
    },
    "trash_can": {
        "precision": 0.75,
        "recall": 0.6,
        "f1-score": 0.6666666666666665,
        "support": 10
    },
    "accuracy": 0.8017492711370262,
    "macro avg": {
        "precision": 0.78199219677423,
        "recall": 0.796912964195497,
        "f1-score": 0.7732033493562643,
        "support": 343
    },
    "weighted avg": {
        "precision": 0.8412899295882941,
        "recall": 0.8017492711370262,
        "f1-score": 0.8081242470495807,
        "support": 343
    }
}