{
    "back_pack": {
        "precision": 0.8888888888888888,
        "recall": 1.0,
        "f1-score": 0.9411764705882353,
        "support": 24
    },
    "bike": {
        "precision": 1.0,
        "recall": 1.0,
        "f1-score": 1.0,
        "support": 16
    },
    "bike_helmet": {
        "precision": 1.0,
        "recall": 0.9130434782608695,
        "f1-score": 0.9545454545454545,
        "support": 23
    },
    "bookcase": {
        "precision": 1.0,
        "recall": 1.0,
        "f1-score": 1.0,
        "support": 7
    },
    "bottle": {
        "precision": 1.0,
        "recall": 1.0,
        "f1-score": 1.0,
        "support": 11
    },
    "calculator": {
        "precision": 0.875,
        "recall": 0.8076923076923077,
        "f1-score": 0.8400000000000001,
        "support": 26
    },
    "desk_chair": {
        "precision": 1.0,
        "recall": 0.9428571428571428,
        "f1-score": 0.9705882352941176,
        "support": 35
    },
    "desk_lamp": {
        "precision": 1.0,
        "recall": 0.6153846153846154,
        "f1-score": 0.761904761904762,
        "support": 13
    },
    "desktop_computer": {
        "precision": 1.0,
        "recall": 0.8125,
        "f1-score": 0.896551724137931,
        "support": 16
    },
    "file_cabinet": {
        "precision": 0.7058823529411765,
        "recall": 0.8571428571428571,
        "f1-score": 0.7741935483870968,
        "support": 14
    },
    "headphones": {
        "precision": 1.0,
        "recall": 1.0,
        "f1-score": 1.0,
        "support": 22
    },
    "keyboard": {
        "precision": 0.8076923076923077,
        "recall": 0.9545454545454546,
        "f1-score": 0.875,
        "support": 22
    },
    "laptop_computer": {
        "precision": 0.9545454545454546,
        "recall": 0.84,
        "f1-score": 0.8936170212765958,
        "support": 25
    },
    "letter_tray": {
        "precision": 0.4375,
        "recall": 1.0,
        "f1-score": 0.6086956521739131,
        "support": 14
    },
    "mobile_phone": {
        "precision": 1.0,
        "recall": 0.6,
        "f1-score": 0.7499999999999999,
        "support": 25
    },
    "monitor": {
        "precision": 0.9696969696969697,
        "recall": 0.8421052631578947,
        "f1-score": 0.9014084507042254,
        "support": 38
    },
    "mouse": {
        "precision": 0.78125,
        "recall": 1.0,
        "f1-score": 0.8771929824561403,
        "support": 25
    },
    "mug": {
        "precision": 0.8461538461538461,
        "recall": 1.0,
        "f1-score": 0.9166666666666666,
        "support": 22
    },
    "paper_notebook": {
        "precision": 0.6451612903225806,
        "recall": 0.8695652173913043,
        "f1-score": 0.7407407407407407,
        "support": 23
    },
    "pen": {
        "precision": 0.8620689655172413,
        "recall": 0.9259259259259259,
        "f1-score": 0.8928571428571429,
        "support": 27
    },
    "phone": {
        "precision": 1.0,
        "recall": 0.8181818181818182,
        "f1-score": 0.9,
        "support": 11
    },
    "printer": {
        "precision": 0.8181818181818182,
        "recall": 0.6,
        "f1-score": 0.6923076923076923,
        "support": 15
    },
    "projector": {
        "precision": 0.6842105263157895,
        "recall": 0.52,
        "f1-score": 0.5909090909090909,
        "support": 25
    },
    "punchers": {
        "precision": 0.6875,
        "recall": 0.5,
        "f1-score": 0.5789473684210527,
        "support": 22
    },
    "ring_binder": {
        "precision": 0.7441860465116279,
        "recall": 0.9142857142857143,
        "f1-score": 0.8205128205128205,
        "support": 35
    },
    "ruler": {
        "precision": 0.7142857142857143,
        "recall": 0.8333333333333334,
        "f1-score": 0.7692307692307692,
        "support": 6
    },
    "scissors": {
        "precision": 0.8695652173913043,
        "recall": 1.0,
        "f1-score": 0.9302325581395349,
        "support": 20
    },
    "speaker": {
        "precision": 0.9375,
        "recall": 0.6,
        "f1-score": 0.7317073170731707,
        "support": 25
    },
    "stapler": {
        "precision": 0.5263157894736842,
        "recall": 0.5263157894736842,
        "f1-score": 0.5263157894736842,
        "support": 19
    },
    "tape_dispenser": {
        "precision": 0.9473684210526315,
        "recall": 1.0,
        "f1-score": 0.972972972972973,
        "support": 18
    },
    "trash_can": {
        "precision": 0.8461538461538461,
        "recall": 0.6875,
        "f1-score": 0.7586206896551724,
        "support": 16
    },
    "accuracy": 0.8375,
    "macro avg": {
        "precision": 0.8564228211330609,
        "recall": 0.8380767392784815,
        "f1-score": 0.8344159974331931,
        "support": 640
    },
    "weighted avg": {
        "precision": 0.8595130600423586,
        "recall": 0.8375,
        "f1-score": 0.8366786278082206,
        "support": 640
    }
}