{
    "0": {
        "precision": 0.9850374064837906,
        "recall": 0.992462311557789,
        "f1-score": 0.988735919899875,
        "support": 1194
    },
    "1": {
        "precision": 0.9813725490196078,
        "recall": 0.9960199004975124,
        "f1-score": 0.988641975308642,
        "support": 1005
    },
    "2": {
        "precision": 0.9767441860465116,
        "recall": 0.9767441860465116,
        "f1-score": 0.9767441860465116,
        "support": 731
    },
    "3": {
        "precision": 0.957037037037037,
        "recall": 0.9817629179331308,
        "f1-score": 0.9692423105776444,
        "support": 658
    },
    "4": {
        "precision": 0.9733542319749217,
        "recall": 0.9524539877300614,
        "f1-score": 0.9627906976744186,
        "support": 652
    },
    "5": {
        "precision": 0.9789674952198852,
        "recall": 0.920863309352518,
        "f1-score": 0.9490268767377201,
        "support": 556
    },
    "6": {
        "precision": 0.9717682020802377,
        "recall": 0.9849397590361446,
        "f1-score": 0.9783096484667165,
        "support": 664
    },
    "7": {
        "precision": 0.8748241912798875,
        "recall": 0.9643410852713178,
        "f1-score": 0.9174041297935103,
        "support": 645
    },
    "8": {
        "precision": 0.9849624060150376,
        "recall": 0.966789667896679,
        "f1-score": 0.9757914338919925,
        "support": 542
    },
    "9": {
        "precision": 0.9777777777777777,
        "recall": 0.8881987577639752,
        "f1-score": 0.9308380797396257,
        "support": 644
    },
    "accuracy": 0.9670827047044301,
    "macro avg": {
        "precision": 0.9661845482934694,
        "recall": 0.962457588308564,
        "f1-score": 0.9637525258136657,
        "support": 7291
    },
    "weighted avg": {
        "precision": 0.9680608331603995,
        "recall": 0.9670827047044301,
        "f1-score": 0.9670769089392555,
        "support": 7291
    }
}